MANIFEST.in
README.rst
setup.py
pumpwood_communication/__init__.py
pumpwood_communication/exceptions.py
pumpwood_communication/microservices.py
pumpwood_communication.egg-info/PKG-INFO
pumpwood_communication.egg-info/SOURCES.txt
pumpwood_communication.egg-info/dependency_links.txt
pumpwood_communication.egg-info/pbr.json
pumpwood_communication.egg-info/requires.txt
pumpwood_communication.egg-info/top_level.txt