Metadata-Version: 1.0
Name: pumpwood-communication
Version: 0.1.3
Summary: Package for inter-PumpWood loging and comunication
Home-page: UNKNOWN
Author: André Andrade Baceti
Author-email: a.baceti@murabei.com
License: UNKNOWN
Platform: UNKNOWN
